freeqdsk/__init__.py
freeqdsk/_fileutils.py
freeqdsk/_typing.py
freeqdsk/_version.py
freeqdsk/aeqdsk.py
freeqdsk/geqdsk.py
freeqdsk/peqdsk.py
freeqdsk-0.5.2.dist-info/LICENSE
freeqdsk-0.5.2.dist-info/METADATA
freeqdsk-0.5.2.dist-info/WHEEL
freeqdsk-0.5.2.dist-info/top_level.txt
freeqdsk-0.5.2.dist-info/RECORD
