Metadata-Version: 2.2
Name: freeqdsk
Version: 0.5.2
Summary: GEQDSK and AEQDSK tokamak equilibrium file reader/writer
Author: Ben Dudson, Peter Hill, Liam Pattinson
License: Copyright 2016 Ben Dudson
Project-URL: Source, https://github.com/freegs-plasma/FreeQDSK
Project-URL: Tracker, https://github.com/freegs-plasma/FreeQDSK/issues
Keywords: GEQDSK,AEQDSK,plasma,equilibrium
Classifier: Programming Language :: Python
Classifier: Development Status :: 3 - Alpha
Classifier: Natural Language :: English
Classifier: Intended Audience :: Science/Research
Classifier: License :: OSI Approved :: MIT License
Classifier: Operating System :: OS Independent
Classifier: Programming Language :: Python
Classifier: Topic :: Software Development :: Libraries :: Python Modules
Classifier: Topic :: Scientific/Engineering :: Physics
Requires-Python: >=3.9
License-File: LICENSE
Requires-Dist: numpy>=1.22
Requires-Dist: fortranformat~=2.0
Provides-Extra: tests
Requires-Dist: pytest>=3.3.0; extra == "tests"
Requires-Dist: pytest-cov; extra == "tests"
Provides-Extra: docs
Requires-Dist: sphinx>=5.3; extra == "docs"
Requires-Dist: sphinx-book-theme>=0.4.0rc1; extra == "docs"
Requires-Dist: sphinx_autodoc_typehints>=1.19; extra == "docs"
Provides-Extra: dev
Requires-Dist: flake8; extra == "dev"
Requires-Dist: black; extra == "dev"
